{"cameraMode":{"drawMode":0,"name":"Shaded","section":"Shading Mode"},"sceneLighting":true,"audioPlay":false,"sceneViewState":{"showFog":true,"showMaterialUpdate":false,"showSkybox":true,"showFlares":true,"showImageEffects":true,"showParticleSystems":true},"in2DMode":false,"pivot":{"x":1.57200026512146,"y":-1.565351963043213,"z":-6.24544620513916},"rotation":{"x":0.05762739107012749,"y":0.9327619671821594,"z":-0.31198418140411379,"w":0.17170476913452149},"size":18.72672462463379,"orthographic":false}